LICENSE
README.md
pyproject.toml
setup.py
motionblindsble/__init__.py
motionblindsble/const.py
motionblindsble/crypt.py
motionblindsble/device.py
motionblindsble/util.py
motionblindsble.egg-info/PKG-INFO
motionblindsble.egg-info/SOURCES.txt
motionblindsble.egg-info/dependency_links.txt
motionblindsble.egg-info/not-zip-safe
motionblindsble.egg-info/requires.txt
motionblindsble.egg-info/top_level.txt